odoo/addons/contract_sale_mandate/README.rst
odoo/addons/contract_sale_mandate/__init__.py
odoo/addons/contract_sale_mandate/__manifest__.py
odoo/addons/contract_sale_mandate/i18n/contract_sale_mandate.pot
odoo/addons/contract_sale_mandate/i18n/de.po
odoo/addons/contract_sale_mandate/i18n/es.po
odoo/addons/contract_sale_mandate/i18n/fr.po
odoo/addons/contract_sale_mandate/i18n/it.po
odoo/addons/contract_sale_mandate/i18n/pt_BR.po
odoo/addons/contract_sale_mandate/models/__init__.py
odoo/addons/contract_sale_mandate/models/sale_order.py
odoo/addons/contract_sale_mandate/readme/CONTRIBUTORS.md
odoo/addons/contract_sale_mandate/readme/DESCRIPTION.md
odoo/addons/contract_sale_mandate/static/description/icon.png
odoo/addons/contract_sale_mandate/static/description/index.html
odoo/addons/contract_sale_mandate/tests/__init__.py
odoo/addons/contract_sale_mandate/tests/test_contract_sale_mandate.py
odoo_addon_contract_sale_mandate-18.0.1.0.0.3.dist-info/METADATA
odoo_addon_contract_sale_mandate-18.0.1.0.0.3.dist-info/WHEEL
odoo_addon_contract_sale_mandate-18.0.1.0.0.3.dist-info/top_level.txt
odoo_addon_contract_sale_mandate-18.0.1.0.0.3.dist-info/RECORD
