Metadata-Version: 2.1
Name: odoo-addon-contract_sale_mandate
Version: 18.0.1.0.0.3
Requires-Python: >=3.10
Requires-Dist: odoo-addon-account_banking_mandate==18.0.*
Requires-Dist: odoo-addon-account_banking_mandate_sale==18.0.*
Requires-Dist: odoo-addon-contract==18.0.*
Requires-Dist: odoo-addon-contract_mandate==18.0.*
Requires-Dist: odoo-addon-product_contract==18.0.*
Requires-Dist: odoo==18.0.*
Summary: This module manages the banking mandate from the sale order to the contract.
Home-page: https://github.com/OCA/contract
License: AGPL-3
Author: ACSONE SA/NV,Odoo Community Association (OCA)
Author-email: support@odoo-community.org
Classifier: Programming Language :: Python
Classifier: Framework :: Odoo
Classifier: Framework :: Odoo :: 18.0
Classifier: License :: OSI Approved :: GNU Affero General Public License v3
